gpso/__init__.py
gpso/callbacks.py
gpso/gp_surrogate.py
gpso/optimisation.py
gpso/param_space.py
gpso/plotting.py
gpso/saving_helper.py
gpso/utils.py
pygpso-0.6.1.dist-info/LICENSE
pygpso-0.6.1.dist-info/METADATA
pygpso-0.6.1.dist-info/WHEEL
pygpso-0.6.1.dist-info/top_level.txt
pygpso-0.6.1.dist-info/RECORD
