Metadata-Version: 2.1
Name: pygpso
Version: 0.6.1
Summary: Bayesian optimisation method leveraging Gaussian Processes surrogate
Home-page: https://github.com/jajcayn/pygpso
Author: Nikola Jajcay
Author-email: nikola.jajcay@protonmail.com
License: MIT
Platform: UNKNOWN
Classifier: Programming Language :: Python :: 3
Classifier: Development Status :: 3 - Alpha
Classifier: License :: OSI Approved :: MIT License
Classifier: Operating System :: OS Independent
Classifier: Intended Audience :: Science/Research
Classifier: Topic :: Scientific/Engineering :: Bio-Informatics
Classifier: Topic :: Scientific/Engineering :: Medical Science Apps.
Requires-Python: >=3.6
Requires-Dist: anytree
Requires-Dist: black
Requires-Dist: dill
Requires-Dist: flake8
Requires-Dist: gpflow (>=2.0.0)
Requires-Dist: json5
Requires-Dist: matplotlib
Requires-Dist: numpy
Requires-Dist: pathos
Requires-Dist: pytest
Requires-Dist: scikit-learn
Requires-Dist: scipy
Provides-Extra: plotting-extras
Requires-Dist: python-igraph ; extra == 'plotting-extras'
Provides-Extra: saving-helper
Requires-Dist: pandas ; extra == 'saving-helper'
